hurst_estimators/__init__.py
hurst_estimators/estimators/__init__.py
hurst_estimators/estimators/central_estimator.py
hurst_estimators/estimators/dfa_estimator.py
hurst_estimators/estimators/ghe_estimator.py
hurst_estimators/estimators/higuchi_estimator.py
hurst_estimators/estimators/periodogram_estimator.py
hurst_estimators/estimators/rs_estimator.py
hurst_estimators/estimators/wavelet_estimator.py
hurst_estimators/simulators/__init__.py
hurst_estimators/simulators/generate_fgn.py
hurst_estimators/utils/__init__.py
hurst_estimators/utils/_gen_sbpf.py
hurst_estimators/utils/search_opt_seq_len.py
hurst_estimators-0.0.3.dist-info/LICENSE
hurst_estimators-0.0.3.dist-info/METADATA
hurst_estimators-0.0.3.dist-info/WHEEL
hurst_estimators-0.0.3.dist-info/RECORD
